setup.py
spoticated/__init__.py
spoticated.egg-info/PKG-INFO
spoticated.egg-info/SOURCES.txt
spoticated.egg-info/dependency_links.txt
spoticated.egg-info/top_level.txt